{"ETH5020M": {"Symbol": "ETH-PERP", "Strategie": "Market", "Marketduration": "change1h", "Threshold": 0.0, "amountpercen": 1, "Leverage": 20, "TargetWIN": 50, "TargetLOSE": 33, "SellAccount": "ETH5020M", "BuyAccount": "ETH5020M", "duration": 120},
"ETH5020O": {"Symbol": "ETH-PERP", "Strategie": "Opposite", "Marketduration": "change1h", "Threshold": 0.0, "amountpercen": 1, "Leverage": 20, "TargetWIN": 50, "TargetLOSE": 33, "SellAccount": "ETH5020O", "BuyAccount": "ETH5020O", "duration": 180},
"ADA1010M": {"Symbol": "ADA-PERP", "Strategie": "Market", "Marketduration": "change1h", "Threshold": 0.0, "amountpercen": 1, "Leverage": 10, "TargetWIN": 10, "TargetLOSE": 9, "SellAccount": "ADA1010M", "BuyAccount": "ADA1010M", "duration": 45},
"ADA1010O": {"Symbol": "ADA-PERP", "Strategie": "Opposite", "Marketduration": "change1h", "Threshold": 0.0, "amountpercen": 1, "Leverage": 10, "TargetWIN": 10, "TargetLOSE": 9, "SellAccount": "ADA1010O", "BuyAccount": "ADA1010O", "duration": 50},
"TRX55M": {"Symbol": "TRX-PERP", "Strategie": "Market", "Marketduration": "change1h", "Threshold": 0.00, "amountpercen": 1, "Leverage": 5, "TargetWIN": 5, "TargetLOSE": 4.7, "SellAccount": "TRX55M", "BuyAccount": "TRX55M", "duration": 55},
"TRX55O": {"Symbol": "TRX-PERP", "Strategie": "Opposite", "Marketduration": "change1h", "Threshold": 0.00, "amountpercen": 1, "Leverage": 5, "TargetWIN": 5, "TargetLOSE": 4.7, "SellAccount": "TRX55O", "BuyAccount": "TRX55O", "duration": 60},
"DOGE520M": {"Symbol": "DOGE-PERP", "Strategie": "Market", "Marketduration": 30, "Threshold": 0.00, "amountpercen": 1, "Leverage": 20, "TargetWIN": 5, "TargetLOSE": 4.7, "SellAccount": "DOGE520M", "BuyAccount": "DOGE520M", "duration": 5},
"DOGE520O": {"Symbol": "DOGE-PERP", "Strategie": "Opposite", "Marketduration": 30, "Threshold": 0.00, "amountpercen": 1, "Leverage": 20, "TargetWIN": 5, "TargetLOSE": 4.7, "SellAccount": "DOGE520O", "BuyAccount": "DOGE520O", "duration": 5},
"DOGE410M": {"Symbol": "DOGE-PERP", "Strategie": "Market", "Marketduration": "change1h", "Threshold": 0.00, "amountpercen": 1, "Leverage": 10, "TargetWIN": 4, "TargetLOSE": 3.8, "SellAccount": "DOGE410M", "BuyAccount": "DOGE410M", "duration": 35},
"DOGE410O": {"Symbol": "DOGE-PERP", "Strategie": "Opposite", "Marketduration": "change1h", "Threshold": 0.00, "amountpercen": 1, "Leverage": 10, "TargetWIN": 4, "TargetLOSE": 3.8, "SellAccount": "DOGE410O", "BuyAccount": "DOGE410O", "duration": 57},
"SRN510M": {"Symbol": "SNX-PERP", "Strategie": "Market", "Marketduration": 30, "Threshold": 0.00, "amountpercen": 1, "Leverage": 10, "TargetWIN": 5.50, "TargetLOSE": 50, "SellAccount": "SRN510M", "BuyAccount": "SRN510M", "duration": 15}}